bonsu-3.7.2.dist-info/RECORD
bonsu-3.7.2.dist-info/WHEEL
bonsu-3.7.2.dist-info/entry_points.txt
bonsu-3.7.2.dist-info/top_level.txt
bonsu-3.7.2.dist-info/METADATA
bonsu/__init__.py
bonsu/interface/instance.py
bonsu/interface/cms.npy
bonsu/interface/panelstdout.py
bonsu/interface/panelpref.py
bonsu/interface/render.py
bonsu/interface/panelvisual.py
bonsu/interface/subpanel.py
bonsu/interface/bonsu.py
bonsu/interface/panelscript.py
bonsu/interface/__init__.py
bonsu/interface/action.py
bonsu/interface/panelgraph.py
bonsu/interface/common.py
bonsu/interface/panelphase.py
bonsu/changelog/CHANGELOG.md
bonsu/changelog/__init__.py
bonsu/phasing/abstract.py
bonsu/phasing/HIO.py
bonsu/phasing/concurrent.py
bonsu/phasing/RAAR.py
bonsu/phasing/__init__.py
bonsu/phasing/ER.py
bonsu/phasing/CSHIO.py
bonsu/phasing/HPR.py
bonsu/phasing/ShrinkWrap.py
bonsu/phasing/SO2D.py
bonsu/phasing/wrap.py
bonsu/docs/Bonsu.pdf
bonsu/docs/docs.zip
bonsu/docs/__init__.py
bonsu/operations/loadarray.py
bonsu/operations/HIO.py
bonsu/operations/memory.py
bonsu/operations/RAAR.py
bonsu/operations/compact.py
bonsu/operations/__init__.py
bonsu/operations/ER.py
bonsu/operations/CSHIO.py
bonsu/operations/POER.py
bonsu/operations/HPR.py
bonsu/operations/SO2D.py
bonsu/operations/wrap.py
bonsu/image/__init__.py
bonsu/image/bonsu.ico
bonsu/image/bonsu.icns
bonsu/.dylibs/libfftw3f_threads.3.dylib
bonsu/.dylibs/libfftw3f.3.dylib
bonsu/.dylibs/libfftw3_threads.3.dylib
bonsu/.dylibs/libfftw3.3.dylib
bonsu/sequences/functions.py
bonsu/sequences/algorithms.py
bonsu/sequences/__init__.py
bonsu/lib/fftwlib.cpp
bonsu/lib/prutillib.cpp
bonsu/lib/prutillib.cpython-311-darwin.so
bonsu/lib/__init__.py
bonsu/lib/fftwlib.cpython-311-darwin.so
bonsu/licence/__init__.py
bonsu/licence/gpl.txt
