Metadata-Version: 2.4
Name: Bonsu
Version: 3.7.2
Summary: Bonsu - The Interactive Phase Retrieval Suite
Author-email: "Marcus C. Newton" <Bonsu.Devel@gmail.com>
Maintainer-email: "Marcus C. Newton" <Bonsu.Devel@gmail.com>
License: GPL3
Project-URL: documentation, https://bonsudev.github.io/bonsu
Project-URL: source, https://github.com/bonsudev/bonsu
Project-URL: home-page, https://github.com/bonsudev/bonsu
Keywords: Phase Retrieval,Bragg Coherent Diffraction Imaging,Synchrotron Science
Requires-Python: >=3.7
Requires-Dist: wxpython>=4.2.0
Requires-Dist: numpy>1.23.0
Requires-Dist: vtk>=8.0.0
Requires-Dist: h5py
Requires-Dist: pillow
Provides-Extra: hdf5plugin
Requires-Dist: hdf5plugin; extra == "hdf5plugin"
